<?xml version="1.0" encoding="utf-8" ?><dwsync><file name="light.css" server="64.207.139.206//home/149360/domains/lacydiamond.com/html/" local="3417211418" remote="12015937726" /><file name="demo.css" server="64.207.139.206//home/149360/domains/lacydiamond.com/html/" local="3409879033" remote="12015937726" /><file name="demo2.css" server="64.207.139.206//home/149360/domains/lacydiamond.com/html/" local="3420227466" remote="12015937727" /><file name="style.css" server="64.207.139.206//home/149360/domains/lacydiamond.com/html/" local="3417740197" remote="12015937730" /><file name="style1.css" server="64.207.139.206//home/149360/domains/lacydiamond.com/html/" local="3426021930" remote="12015956526" /><file name="style2.css" server="64.207.139.206//home/149360/domains/lacydiamond.com/html/" local="3409874765" remote="12015937774" /><file name="style3.css" server="64.207.139.206//home/149360/domains/lacydiamond.com/html/" local="3409874765" remote="12015937774" /><file name="style4.css" server="64.207.139.206//home/149360/domains/lacydiamond.com/html/" local="3409874765" remote="12015937774" /></dwsync>